Metadata-Version: 2.1
Name: poetree
Version: 0.0.1
Summary: An easy way to get data from PoeTree dataset
Home-page: https://github.com/versotym/poetree
Download-URL: https://github.com/versotym/poetree/archive/v0.0.1.tar.gz
Author: Petr Plechac
Author-email: plechac@ucl.cas.cz
License: MIT
Keywords: poetry,corpus,versification
Classifier: Development Status :: 4 - Beta
Classifier: Intended Audience :: Developers
Classifier: Topic :: Text Processing :: Linguistic
Classifier: License :: OSI Approved :: MIT License
Classifier: Programming Language :: Python :: 3
Classifier: Programming Language :: Python :: 3.1
Classifier: Programming Language :: Python :: 3.2
Classifier: Programming Language :: Python :: 3.3
Classifier: Programming Language :: Python :: 3.4
Classifier: Programming Language :: Python :: 3.5
Classifier: Programming Language :: Python :: 3.6
Classifier: Programming Language :: Python :: 3.7
Classifier: Programming Language :: Python :: 3.8
Classifier: Programming Language :: Python :: 3.9
Classifier: Programming Language :: Python :: 3.10
License-File: LICENSE.txt
